abobuilder/__init__.py
abobuilder/_version.py
abobuilder/abobuilder.py
abobuilder/element_table.py
abobuilder-0.1.2.dist-info/licenses/LICENSE
abobuilder-0.1.2.dist-info/METADATA
abobuilder-0.1.2.dist-info/WHEEL
abobuilder-0.1.2.dist-info/top_level.txt
abobuilder-0.1.2.dist-info/RECORD
