Metadata-Version: 2.4
Name: abobuilder
Version: 0.1.2
Summary: abobuilder
Home-page: https://www.github.com/ifilot/abobuilder
Author: Ivo Filot
Author-email: Ivo Filot <i.a.w.filot@tue.nl>
Maintainer-email: Ivo Filot <i.a.w.filot@tue.nl>
License: GPL-3.0-or-later
Project-URL: Homepage, https://www.github.com/ifilot/abobuilder
Project-URL: Bug Tracker, https://www.github.com/ifilot/abobuilder/issues
Classifier: Programming Language :: Python :: 3
Classifier: Operating System :: OS Independent
Requires-Python: >=3.5
License-File: LICENSE
Requires-Dist: scipy
Requires-Dist: numpy
Requires-Dist: pyqint
Requires-Dist: pytessel
Dynamic: author
Dynamic: home-page
Dynamic: license-file
Dynamic: requires-python
